openseneca/__init__.py
openseneca/config.yml
openseneca/costs.py
openseneca/router.py
openseneca/weights.pk
openseneca/classify/__init__.py
openseneca/classify/categories.py
openseneca/classify/llm.py
openseneca/classify/static.py
openseneca/interfaces/__init__.py
openseneca/interfaces/models.py
openseneca/interfaces/providers.py
openseneca/interfaces/response.py
openseneca/models/__init__.py
openseneca/models/cohere.py
openseneca/models/gpt3.py
openseneca/models/gpt4.py
openseneca/models/llama2.py
openseneca/models/llama3.py
openseneca/models/mistral.py
openseneca/providers/__init__.py
openseneca/providers/azure.py
openseneca/utils/__init__.py
openseneca/utils/inspection.py
openseneca/utils/logger.py
ranking/__init__.py
ranking/battle.py
ranking/dataset.py
ranking/evaluator.py
ranking/ranking.py
tests/__init__.py
tests/_dummies.py
tests/test_gpt3.py
tests/test_gpt4.py
tests/test_inspection.py
tests/test_llama2.py
tests/test_mistral.py
openseneca-0.1.1.dist-info/LICENSE
openseneca-0.1.1.dist-info/METADATA
openseneca-0.1.1.dist-info/WHEEL
openseneca-0.1.1.dist-info/top_level.txt
openseneca-0.1.1.dist-info/RECORD
