Metadata-Version: 2.1
Name: openseneca
Version: 0.1.1
Summary: OpenSeneca
Author: Ottavio Fogliata
Author-email: ottavio.fogliata@openseneca.ai
Keywords: python
Requires-Python: >=3.8.13
License-File: LICENSE
Requires-Dist: fire >=0.6.0
Requires-Dist: uvicorn[standard] >=0.29.0
Requires-Dist: fastapi >=0.110.1
Requires-Dist: pytest
Requires-Dist: pandas >=2.0.3
Requires-Dist: torch ==2.2.1
Requires-Dist: transformers >=4.38.2
Requires-Dist: safetensors
Requires-Dist: scikit-learn >=1.3.2
Requires-Dist: evaluate >=0.4.1
Requires-Dist: lm-eval >=0.4.2
Requires-Dist: langchain >=0.1.13
Requires-Dist: openai >=1.14.2
Requires-Dist: langchain-openai >=0.1.1
Requires-Dist: tqdm
Requires-Dist: pylint
Requires-Dist: pytest-cov
Requires-Dist: colorlog
Requires-Dist: pycountry
Requires-Dist: python-dotenv
Requires-Dist: langdetect
Requires-Dist: pydantic
Requires-Dist: huggingface-cli
